probconslib.so
reveallib.so
reveallib64.so
reveal/__init__.py
reveal/align.py
reveal/annotate.py
reveal/bubbles.py
reveal/chain.py
reveal/chop.py
reveal/comp.py
reveal/convert.py
reveal/extract.py
reveal/matches.py
reveal/merge.py
reveal/plot.py
reveal/refine.py
reveal/rem.py
reveal/reveal.py
reveal/schemes.py
reveal/split.py
reveal/stats.py
reveal/subgraph.py
reveal/transform.py
reveal/transformold.py
reveal/unzip.py
reveal/utils.py
reveal-0.2.2.data/scripts/ez_setup.py
reveal-0.2.2.dist-info/LICENSE.txt
reveal-0.2.2.dist-info/METADATA
reveal-0.2.2.dist-info/WHEEL
reveal-0.2.2.dist-info/entry_points.txt
reveal-0.2.2.dist-info/top_level.txt
reveal-0.2.2.dist-info/RECORD
